{
  "visualType": "lineChart",
  "projections": {
    "Category": [
      {
        "queryRef": "Orders.Order Date"
      }
    ],
    "Values": [
      {
        "queryRef": "Orders.__tableau_internal_object_id__"
      }
    ]
  },
  "prototypeQuery": {
    "Version": 2,
    "From": [
      {
        "Name": "Orders",
        "Entity": "Orders"
      }
    ],
    "Select": [
      {
        "Column": {
          "Expression": {
            "SourceRef": {
              "Source": "Orders"
            }
          },
          "Property": "Order Date"
        },
        "Name": "Orders.Order Date"
      },
      {
        "Column": {
          "Expression": {
            "SourceRef": {
              "Source": "Orders"
            }
          },
          "Property": "__tableau_internal_object_id__"
        },
        "Name": "Orders.__tableau_internal_object_id__"
      }
    ]
  },
  "objects": {
    "title": [
      {
        "properties": {
          "text": {
            "expr": {
              "Literal": {
                "Value": "'ShippingTrend'"
              }
            }
          }
        }
      }
    ]
  }
}