{
  "$schema": "https://developer.microsoft.com/json-schemas/fabric/item/report/definition/visualContainer/2.5.0/schema.json",
  "name": "cd34ef56ab7890cd",
  "position": {
    "x": 20,
    "y": 410,
    "z": 3,
    "height": 260,
    "width": 1220,
    "tabOrder": 3
  },
  "visual": {
    "visualType": "filledMap",
    "query": {
      "queryState": {
        "Location": {
          "projections": [
            {
              "field": {
                "Column": {
                  "Expression": {
                    "SourceRef": {
                      "Entity": "Orders"
                    }
                  },
                  "Property": "State/Province"
                }
              },
              "queryRef": "Orders.State/Province",
              "nativeQueryRef": "State/Province",
              "active": true
            }
          ]
        },
        "Color": {
          "projections": [
            {
              "field": {
                "Aggregation": {
                  "Expression": {
                    "Column": {
                      "Expression": {
                        "SourceRef": {
                          "Entity": "Orders"
                        }
                      },
                      "Property": "Profit"
                    }
                  },
                  "Function": 0
                }
              },
              "queryRef": "Sum(Orders.Profit)",
              "nativeQueryRef": "Sum of Profit"
            }
          ]
        }
      }
    },
    "drillFilterOtherVisuals": true,
    "autoSelectVisualType": true
  },
  "filterConfig": {
    "filters": [
      {
        "name": "map_location_filter",
        "field": {
          "Column": {
            "Expression": {
              "SourceRef": {
                "Entity": "Orders"
              }
            },
            "Property": "State/Province"
          }
        },
        "type": "Categorical"
      },
      {
        "name": "map_profit_filter",
        "field": {
          "Aggregation": {
            "Expression": {
              "Column": {
                "Expression": {
                  "SourceRef": {
                    "Entity": "Orders"
                  }
                },
                "Property": "Profit"
              }
            },
            "Function": 0
          }
        },
        "type": "Advanced"
      }
    ]
  }
}