{
  "$schema": "https://developer.microsoft.com/json-schemas/fabric/item/report/definition/visualContainer/2.5.0/schema.json",
  "name": "exec_store_type_slicer",
  "position": {
    "x": 960,
    "y": 380,
    "z": 9,
    "height": 200,
    "width": 280,
    "tabOrder": 9
  },
  "visual": {
    "visualType": "slicer",
    "autoSelectVisualType": true,
    "query": {
      "queryState": {
        "Values": {
          "projections": [
            {
              "field": {
                "Column": {
                  "Expression": {
                    "SourceRef": {
                      "Entity": "Retail Sales Data"
                    }
                  },
                  "Property": "Store Type"
                }
              },
              "queryRef": "Retail Sales Data.Store Type",
              "nativeQueryRef": "Store Type"
            }
          ]
        }
      }
    },
    "drillFilterOtherVisuals": true
  }
}
